README.rst
setup.py
bin/pyimgconvert
pyimgconvert/pyimgconvert.py
pyimgconvert.egg-info/PKG-INFO
pyimgconvert.egg-info/SOURCES.txt
pyimgconvert.egg-info/dependency_links.txt
pyimgconvert.egg-info/not-zip-safe
pyimgconvert.egg-info/requires.txt
pyimgconvert.egg-info/top_level.txt