Metadata-Version: 1.0
Name: pyimgconvert
Version: 1.0.10
Summary: (Python) utility which acts as a wrapper around the Linux CLI: convert
Home-page: https://github.com/FNNDSC/pyimgconvert
Author: FNNDSC
Author-email: dev@babymri.org
License: MIT
Platform: UNKNOWN
